{
   "id": 10,
   "title": "Mentalne aspekty biegania: jak utrzymać motywację",
   "author": "Katarzyna Szymczak",
   "image": "/images/article-images/motywacja-bieganie.jpg",
   "text": "Motywacja jest kluczowa dla sukcesu biegacza. Dowiedz się, jak utrzymać wysoki poziom motywacji, jak ustalać cele oraz jak radzić sobie z trudnościami, które mogą się pojawić w trakcie treningów.\n\n**1. Ustal cele**\nPostaw sobie realistyczne cele, np. przebiegnięcie 5 km lub udział w zawodach. Cele pomagają utrzymać motywację.\n\n**2. Znajdź partnera do biegania**\nBieganie z przyjacielem lub grupą biegową zwiększa motywację i sprawia, że treningi są przyjemniejsze.\n\n**3. Nagradzaj się**\nPo osiągnięciu celu nagradzaj się, np. nowymi butami biegowymi lub masażem.\n\n**4. Różnicuj treningi**\nUnikaj monotonii. Włącz do planu treningowego różne rodzaje biegów, np. interwały, biegi długodystansowe czy trailowe.\n\n**5. Słuchaj swojego ciała**\nJeśli czujesz zmęczenie lub brak motywacji, zrób przerwę. Regeneracja jest kluczowa dla długotrwałego sukcesu.\n\nMotywacja to klucz do regularnego biegania. Znajdź swój sposób na utrzymanie entuzjazmu i ciesz się każdym treningiem!"
}
